pyke/__init__.py
pyke/core.py
pyke/errors.py
pyke/runner.py
pyke/task.py
pykefile-0.0.4.dist-info/LICENSE
pykefile-0.0.4.dist-info/METADATA
pykefile-0.0.4.dist-info/WHEEL
pykefile-0.0.4.dist-info/entry_points.txt
pykefile-0.0.4.dist-info/top_level.txt
pykefile-0.0.4.dist-info/RECORD
