Metadata-Version: 2.1
Name: pykefile
Version: 0.0.4
Summary: Make-like build automation tool for Python projects.
Home-page: UNKNOWN
License: MIT
Project-URL: Source Code, https://github.com/frissyn/pyke
Project-URL: Pull Requests, https://github.com/frissyn/pyke/pulls
Project-URL: Issue Tracker, https://github.com/frissyn/pyke/issues
Platform: UNKNOWN
Classifier: License :: OSI Approved :: MIT License
Classifier: Intended Audience :: Developers
Classifier: Operating System :: OS Independent
Classifier: Programming Language :: Python :: 3.8
Classifier: Programming Language :: Python :: 3.9
Classifier: Topic :: Software Development
Classifier: Topic :: Software Development :: Build Tools
Requires-Python: >=3.8.0
License-File: LICENSE
